tests/__init__.py
unifi/__init__.py
unifi/clock_sync.py
unifi/core.py
unifi/main.py
unifi/version.py
unifi/cams/__init__.py
unifi/cams/base.py
unifi/cams/dahua.py
unifi/cams/frigate.py
unifi/cams/hikvision.py
unifi/cams/lorex.py
unifi/cams/reolink.py
unifi/cams/reolink_nvr.py
unifi/cams/rtsp.py
unifi/cams/unifi.py
unifi_cam_proxy-0.2.0.dist-info/LICENSE
unifi_cam_proxy-0.2.0.dist-info/METADATA
unifi_cam_proxy-0.2.0.dist-info/WHEEL
unifi_cam_proxy-0.2.0.dist-info/entry_points.txt
unifi_cam_proxy-0.2.0.dist-info/top_level.txt
unifi_cam_proxy-0.2.0.dist-info/RECORD
